gaddag/__init__.py
gaddag/cgaddag.py
gaddag/gaddag.py
gaddag/libcgaddag.so
gaddag/node.py
GADDAG-1.0.1.dist-info/LICENSE
GADDAG-1.0.1.dist-info/METADATA
GADDAG-1.0.1.dist-info/WHEEL
GADDAG-1.0.1.dist-info/top_level.txt
GADDAG-1.0.1.dist-info/RECORD
