Metadata-Version: 2.1
Name: GADDAG
Version: 1.0.1
Summary: Python wrapper around cGADDAG
Home-page: https://git.sr.ht/~jorbas/GADDAG
Author: Jordan Bass
Author-email: jordan@jbass.io
License: MIT
Download-URL: https://git.sr.ht/~jorbas/GADDAG/archive/1.0.1.tar.gz
Platform: any
Requires-Python: >=3
